app/__init__.py
app/__version__.py
app/app.py
flask_boilerplate-1.0.4.dist-info/LICENSE
flask_boilerplate-1.0.4.dist-info/METADATA
flask_boilerplate-1.0.4.dist-info/WHEEL
flask_boilerplate-1.0.4.dist-info/top_level.txt
flask_boilerplate-1.0.4.dist-info/RECORD
