Metadata-Version: 2.1
Name: flask-boilerplate
Version: 1.0.4
Summary: Boilerplate for Flask API
Home-page: https://github.com/openboilerplates/flask-boilerplate
Author: Fakabbir Amin
Author-email: fakabbir@gmail.com
License: UNKNOWN
Platform: UNKNOWN
Classifier: License :: OSI Approved :: MIT License
Classifier: Programming Language :: Python :: 2.7
Classifier: Programming Language :: Python :: 3.5
Classifier: Programming Language :: Python :: 3.6
Classifier: Programming Language :: Python :: 3.7
Requires-Python: >=3.6
